Workbook

Sheet CoverPage
A1: FINANCIAL MODELING USING EXCEL
A3: Capital Rationing Decision Models Using Excel
A5: Optimal Project Selection Under Capital Constraints | I5: Learning Philosophy
A7: Workbook Purpose | I7: When capital is scarce, value is created by choosing the right combination of projects—not by evaluating projects in isolation.
A9: This workbook is designed to analyze capital rationing problems, where a firm must select an optimal combination of investment projects subject to limited capital availability. It presents six structured caselets that require evaluating mutually independent projects, comparing value creation, and identifying the project mix that maximizes total Net Present Value (NPV) under budget constraints. The workbook emphasizes optimization-based decision-making rather than isolated project evaluation. By structuring project cash flows, computing NPVs, and applying optimization logic in Excel, learners understand how capital rationing transforms capital budgeting into a constrained optimization problem—a setting commonly faced by firms with funding limits, divisional budgets, or capital allocation policies.
A15: Key Concepts Covered | I15: Excel Functions Used
A16: Capital rationing and funding constraints Independent projects and value creation under scarcity Net Present Value (NPV) as the objective function Capital budgeting with single and multiple constraints Project selection versus project ranking Limitations of simple profitability index ranking Optimization logic for maximizing firm value Interpretation of optimal project combinations Managerial implications of constrained investment decisions | I16: The following Excel functions and tools are used accurately and completely in this workbook to support valuation, constraint handling, and optimization: NPV – Computes the present value of each project’s cash flows SUM – Aggregates selected project investments and NPVs SUMPRODUCT – Computes total NPV and total capital usage based on project selection variables IF – Applies conditional logic for project inclusion and feasibility checks ABS – Maintains disciplined sign conventions for cash flows ROUND – Ensures numerical clarity and clean presentation of results PERCENTAGE CALCULATIONS – Used for discount rates and capital usage interpretation Excel Optimization Tool Solver (Excel Add-in) – Identifies the optimal combination of projects by maximizing total NPV subject to capital constraints and binary decision variables The workbook emphasizes correct problem formulation, clear definition of objective and constraints, and transparent interpretation of Solver outputs.
E18: Srikanth Potharla is an accounting and finance educator with over fifteen years of teaching and industry-oriented experience. Currently serving as Assistant Professor at ICFAI Business School, Hyderabad, he specializes in financial modeling using Excel, valuation, and data analytics. His work bridges theory and practice through structured models, real-world applications, and hands-on learning resources designed for MBA, professional, and global learners.

Sheet INDEX
A1: Capital Rationing (Capital Budgeting) – 6 Caselets (Excel Solver Model)
A3: Use the links below. Each caselet sheet contains Inputs + Calculations + Outputs + Checks (single-sheet model).
A5: Caselet | B5: Company | C5: Constraint theme | D5: Open
A6: Caselet 1 | B6: Optimus Solutions | C6: Mutual exclusivity + dependency + mandatory project | D6: Open ➜
A7: Caselet 2 | B7: NovaTech Inc. | C7: Min/Max project count + mutual inclusion | D7: Open ➜
A8: Caselet 3 | B8: InnovateCorp | C8: Exclude low-value + include core group + include high NPV set | D8: Open ➜
A9: Caselet 4 | B9: FutureVision Ltd. | C9: Pairing + group cost cap | D9: Open ➜
A10: Caselet 5 | B10: VisionNext Ltd. | C10: NPV threshold + min high-cost + conflict pair | D10: Open ➜
A11: Caselet 6 | B11: GlobalTech Ltd. | C11: Strategic allocation + risk cap + portfolio ratio | D11: Open ➜
A13: Project data table: | B13: Open ➜
A14: Checks summary: | B14: Open ➜

Sheet PROJECT_DATA
A1: Common Project Data (Cost & NPV)
A3: All caselets refer to this table for project-wise Cost and NPV.
A5: Capital Budget (₹) | B5: 5000000
A7: Project | B7: Cost (₹) | C7: NPV (₹)
A8: A | B8: 800000 | C8: 240000
A9: B | B9: 650000 | C9: 180000
A10: C | B10: 750000 | C10: 210000
A11: D | B11: 900000 | C11: 270000
A12: E | B12: 550000 | C12: 120000
A13: F | B13: 600000 | C13: 195000
A14: G | B14: 450000 | C14: 95000
A15: H | B15: 350000 | C15: 75000
A16: I | B16: 500000 | C16: 135000
A17: J | B17: 400000 | C17: 105000
A19: Total cost (all projects) | B19: =SUM(B8:B17)

Sheet Caselet_01_Optimus
A1: Caselet 1 – Capital Allocation Decision at Optimus Solutions
A2: ⬅ Back to Index
B4: INPUTS | I4: OUTPUTS / DECISION
B5: Capital Budget (₹) | C5: =PROJECT_DATA!$B$5 | I5: Key Outputs
B6: Objective | C6: Maximize Total NPV | I6: Metric | J6: Value
B7: Decision variables | C7: Select? (0/1) for each project | I7: Total Cost (₹) | J7: =C23
B8: Solver note | C8: Objective: C24 (Total NPV). Variable cells: E12:E21 (Binary). Add constraints in Checks. | I8: Total NPV (₹) | J8: =C24
C9: Pre-filled with an optimal solution (computed and saved). You may re-run Solver after changing any input/constraint. | I9: Budget Slack (₹) | J9: =C25
B10: Project Portfolio (Cost & NPV referenced from PROJECT_DATA) | I10: Projects Selected | J10: =C26
B11: Project | C11: Cost (₹) | D11: NPV (₹) | E11: Select? (0/1) | F11: Selected Cost (₹) | G11: Selected NPV (₹)
B12: A | C12: =VLOOKUP(B12,PROJECT_DATA!$A$8:$C$17,2,FALSE) | D12: =VLOOKUP(B12,PROJECT_DATA!$A$8:$C$17,3,FALSE) | E12: 1 | F12: =C12*E12 | G12: =D12*E12 | I12: CHECKS
B13: B | C13: =VLOOKUP(B13,PROJECT_DATA!$A$8:$C$17,2,FALSE) | D13: =VLOOKUP(B13,PROJECT_DATA!$A$8:$C$17,3,FALSE) | E13: 1 | F13: =C13*E13 | G13: =D13*E13 | I13: Check / Constraint | J13: Status
B14: C | C14: =VLOOKUP(B14,PROJECT_DATA!$A$8:$C$17,2,FALSE) | D14: =VLOOKUP(B14,PROJECT_DATA!$A$8:$C$17,3,FALSE) | E14: 1 | F14: =C14*E14 | G14: =D14*E14 | I14: Budget: Total Cost ≤ Budget | J14: =IF($C$23<=$C$5,"OK","Review")
B15: D | C15: =VLOOKUP(B15,PROJECT_DATA!$A$8:$C$17,2,FALSE) | D15: =VLOOKUP(B15,PROJECT_DATA!$A$8:$C$17,3,FALSE) | E15: 1 | F15: =C15*E15 | G15: =D15*E15 | I15: Binary inputs (0/1) in Select? column | J15: =IF(COUNTIF($E$12:$E$21,"<0")+COUNTIF($E$12:$E$21,">1")=0,"OK","Review")
B16: E | C16: =VLOOKUP(B16,PROJECT_DATA!$A$8:$C$17,2,FALSE) | D16: =VLOOKUP(B16,PROJECT_DATA!$A$8:$C$17,3,FALSE) | E16: 1 | F16: =C16*E16 | G16: =D16*E16 | I16: Mutually exclusive: A and B (EA + EB ≤ 1) | J16: =IF($E$12+$E$13<=1,"OK","Review")
B17: F | C17: =VLOOKUP(B17,PROJECT_DATA!$A$8:$C$17,2,FALSE) | D17: =VLOOKUP(B17,PROJECT_DATA!$A$8:$C$17,3,FALSE) | E17: 1 | F17: =C17*E17 | G17: =D17*E17 | I17: Dependency: D → E (ED ≤ EE) | J17: =IF($E$15<=$E$16,"OK","Review")
B18: G | C18: =VLOOKUP(B18,PROJECT_DATA!$A$8:$C$17,2,FALSE) | D18: =VLOOKUP(B18,PROJECT_DATA!$A$8:$C$17,3,FALSE) | E18: 1 | F18: =C18*E18 | G18: =D18*E18 | I18: Mandatory: F must be selected (EF = 1) | J18: =IF($E$17=1,"OK","Review")
B19: H | C19: =VLOOKUP(B19,PROJECT_DATA!$A$8:$C$17,2,FALSE) | D19: =VLOOKUP(B19,PROJECT_DATA!$A$8:$C$17,3,FALSE) | E19: 1 | F19: =C19*E19 | G19: =D19*E19
B20: I | C20: =VLOOKUP(B20,PROJECT_DATA!$A$8:$C$17,2,FALSE) | D20: =VLOOKUP(B20,PROJECT_DATA!$A$8:$C$17,3,FALSE) | E20: 1 | F20: =C20*E20 | G20: =D20*E20 | I20: Overall Status (all checks) | J20: =IF(COUNTIF($J$14:$J$18,"Review")=0,"OK","Review")
B21: J | C21: =VLOOKUP(B21,PROJECT_DATA!$A$8:$C$17,2,FALSE) | D21: =VLOOKUP(B21,PROJECT_DATA!$A$8:$C$17,3,FALSE) | E21: 1 | F21: =C21*E21 | G21: =D21*E21
B22: CALCULATIONS | I22: Solver Setup (enter in Excel Solver)
B23: Total Cost (₹) | C23: =SUM(F12:F21) | I23: Set Objective | J23: C24 (Total NPV)
B24: Total NPV (₹) | C24: =SUM(G12:G21) | I24: To | J24: Max
B25: Budget Slack (₹) | C25: =$C$5-$C$23 | I25: By Changing Variable Cells | J25: E12:E21
B26: Projects Selected (count) | C26: =SUM(E12:E21) | I26: Constraints (core) | J26: C23 <= C5; E12:E21 Binary
I27: Solving Method | J27: Simplex LP
B28: Constraint helper calculations
B29: Cost(ABC) | C29: =SUMPRODUCT(--ISNUMBER(MATCH($B$12:$B$21,{"A","B","C"},0)),$C$12:$C$21,$E$12:$E$21)
B30: Cost(ACF) | C30: =SUMPRODUCT(--ISNUMBER(MATCH($B$12:$B$21,{"A","C","F"},0)),$C$12:$C$21,$E$12:$E$21)
B31: Cost(DEG) | C31: =SUMPRODUCT(--ISNUMBER(MATCH($B$12:$B$21,{"D","E","G"},0)),$C$12:$C$21,$E$12:$E$21)
B32: High-cost count (Cost>₹7,00,000) | C32: =SUMPRODUCT(--($C$12:$C$21>700000),$E$12:$E$21)
B33: NPV/Cost ratio | C33: =IF($C$23=0,"",$C$24/$C$23)

Sheet Caselet_02_NovaTech
A1: Caselet 2 – Portfolio Selection at NovaTech Inc.
A2: ⬅ Back to Index
B4: INPUTS | I4: OUTPUTS / DECISION
B5: Capital Budget (₹) | C5: =PROJECT_DATA!$B$5 | I5: Key Outputs
B6: Objective | C6: Maximize Total NPV | I6: Metric | J6: Value
B7: Decision variables | C7: Select? (0/1) for each project | I7: Total Cost (₹) | J7: =C23
B8: Solver note | C8: Objective: C24 (Total NPV). Variable cells: E12:E21 (Binary). Add constraints in Checks. | I8: Total NPV (₹) | J8: =C24
C9: Pre-filled with an optimal solution (computed and saved). You may re-run Solver after changing any input/constraint. | I9: Budget Slack (₹) | J9: =C25
B10: Project Portfolio (Cost & NPV referenced from PROJECT_DATA) | I10: Projects Selected | J10: =C26
B11: Project | C11: Cost (₹) | D11: NPV (₹) | E11: Select? (0/1) | F11: Selected Cost (₹) | G11: Selected NPV (₹)
B12: A | C12: =VLOOKUP(B12,PROJECT_DATA!$A$8:$C$17,2,FALSE) | D12: =VLOOKUP(B12,PROJECT_DATA!$A$8:$C$17,3,FALSE) | E12: 1 | F12: =C12*E12 | G12: =D12*E12 | I12: CHECKS
B13: B | C13: =VLOOKUP(B13,PROJECT_DATA!$A$8:$C$17,2,FALSE) | D13: =VLOOKUP(B13,PROJECT_DATA!$A$8:$C$17,3,FALSE) | E13: 1 | F13: =C13*E13 | G13: =D13*E13 | I13: Check / Constraint | J13: Status
B14: C | C14: =VLOOKUP(B14,PROJECT_DATA!$A$8:$C$17,2,FALSE) | D14: =VLOOKUP(B14,PROJECT_DATA!$A$8:$C$17,3,FALSE) | E14: 1 | F14: =C14*E14 | G14: =D14*E14 | I14: Budget: Total Cost ≤ Budget | J14: =IF($C$23<=$C$5,"OK","Review")
B15: D | C15: =VLOOKUP(B15,PROJECT_DATA!$A$8:$C$17,2,FALSE) | D15: =VLOOKUP(B15,PROJECT_DATA!$A$8:$C$17,3,FALSE) | E15: 1 | F15: =C15*E15 | G15: =D15*E15 | I15: Binary inputs (0/1) in Select? column | J15: =IF(COUNTIF($E$12:$E$21,"<0")+COUNTIF($E$12:$E$21,">1")=0,"OK","Review")
B16: E | C16: =VLOOKUP(B16,PROJECT_DATA!$A$8:$C$17,2,FALSE) | D16: =VLOOKUP(B16,PROJECT_DATA!$A$8:$C$17,3,FALSE) | E16: 1 | F16: =C16*E16 | G16: =D16*E16 | I16: Minimum projects selected (SUM E ≥ 5) | J16: =IF($C$26>=5,"OK","Review")
B17: F | C17: =VLOOKUP(B17,PROJECT_DATA!$A$8:$C$17,2,FALSE) | D17: =VLOOKUP(B17,PROJECT_DATA!$A$8:$C$17,3,FALSE) | E17: 1 | F17: =C17*E17 | G17: =D17*E17 | I17: Maximum projects selected (SUM E ≤ 7) | J17: =IF($C$26<=7,"OK","Review")
B18: G | C18: =VLOOKUP(B18,PROJECT_DATA!$A$8:$C$17,2,FALSE) | D18: =VLOOKUP(B18,PROJECT_DATA!$A$8:$C$17,3,FALSE) | E18: 1 | F18: =C18*E18 | G18: =D18*E18 | I18: Mutual inclusion: G → H (EG ≤ EH) | J18: =IF($E$18<=$E$19,"OK","Review")
B19: H | C19: =VLOOKUP(B19,PROJECT_DATA!$A$8:$C$17,2,FALSE) | D19: =VLOOKUP(B19,PROJECT_DATA!$A$8:$C$17,3,FALSE) | E19: 1 | F19: =C19*E19 | G19: =D19*E19
B20: I | C20: =VLOOKUP(B20,PROJECT_DATA!$A$8:$C$17,2,FALSE) | D20: =VLOOKUP(B20,PROJECT_DATA!$A$8:$C$17,3,FALSE) | E20: 1 | F20: =C20*E20 | G20: =D20*E20 | I20: Overall Status (all checks) | J20: =IF(COUNTIF($J$14:$J$18,"Review")=0,"OK","Review")
B21: J | C21: =VLOOKUP(B21,PROJECT_DATA!$A$8:$C$17,2,FALSE) | D21: =VLOOKUP(B21,PROJECT_DATA!$A$8:$C$17,3,FALSE) | E21: 1 | F21: =C21*E21 | G21: =D21*E21
B22: CALCULATIONS | I22: Solver Setup (enter in Excel Solver)
B23: Total Cost (₹) | C23: =SUM(F12:F21) | I23: Set Objective | J23: C24 (Total NPV)
B24: Total NPV (₹) | C24: =SUM(G12:G21) | I24: To | J24: Max
B25: Budget Slack (₹) | C25: =$C$5-$C$23 | I25: By Changing Variable Cells | J25: E12:E21
B26: Projects Selected (count) | C26: =SUM(E12:E21) | I26: Constraints (core) | J26: C23 <= C5; E12:E21 Binary
I27: Solving Method | J27: Simplex LP
B28: Constraint helper calculations
B29: Cost(ABC) | C29: =SUMPRODUCT(--ISNUMBER(MATCH($B$12:$B$21,{"A","B","C"},0)),$C$12:$C$21,$E$12:$E$21)
B30: Cost(ACF) | C30: =SUMPRODUCT(--ISNUMBER(MATCH($B$12:$B$21,{"A","C","F"},0)),$C$12:$C$21,$E$12:$E$21)
B31: Cost(DEG) | C31: =SUMPRODUCT(--ISNUMBER(MATCH($B$12:$B$21,{"D","E","G"},0)),$C$12:$C$21,$E$12:$E$21)
B32: High-cost count (Cost>₹7,00,000) | C32: =SUMPRODUCT(--($C$12:$C$21>700000),$E$12:$E$21)
B33: NPV/Cost ratio | C33: =IF($C$23=0,"",$C$24/$C$23)

Sheet Caselet_03_InnovateCorp
A1: Caselet 3 – Capital Budgeting Decision at InnovateCorp
A2: ⬅ Back to Index
B4: INPUTS | I4: OUTPUTS / DECISION
B5: Capital Budget (₹) | C5: =PROJECT_DATA!$B$5 | E5: Low NPV cutoff (₹) | F5: 100000 | I5: Key Outputs
B6: Objective | C6: Maximize Total NPV | E6: High NPV cutoff (₹) | F6: 200000 | I6: Metric | J6: Value
B7: Decision variables | C7: Select? (0/1) for each project | I7: Total Cost (₹) | J7: =C23
B8: Solver note | C8: Objective: C24 (Total NPV). Variable cells: E12:E21 (Binary). Add constraints in Checks. | I8: Total NPV (₹) | J8: =C24
C9: Pre-filled with an optimal solution (computed and saved). You may re-run Solver after changing any input/constraint. | I9: Budget Slack (₹) | J9: =C25
B10: Project Portfolio (Cost & NPV referenced from PROJECT_DATA) | I10: Projects Selected | J10: =C26
B11: Project | C11: Cost (₹) | D11: NPV (₹) | E11: Select? (0/1) | F11: Selected Cost (₹) | G11: Selected NPV (₹)
B12: A | C12: =VLOOKUP(B12,PROJECT_DATA!$A$8:$C$17,2,FALSE) | D12: =VLOOKUP(B12,PROJECT_DATA!$A$8:$C$17,3,FALSE) | E12: 1 | F12: =C12*E12 | G12: =D12*E12 | I12: CHECKS
B13: B | C13: =VLOOKUP(B13,PROJECT_DATA!$A$8:$C$17,2,FALSE) | D13: =VLOOKUP(B13,PROJECT_DATA!$A$8:$C$17,3,FALSE) | E13: 1 | F13: =C13*E13 | G13: =D13*E13 | I13: Check / Constraint | J13: Status
B14: C | C14: =VLOOKUP(B14,PROJECT_DATA!$A$8:$C$17,2,FALSE) | D14: =VLOOKUP(B14,PROJECT_DATA!$A$8:$C$17,3,FALSE) | E14: 1 | F14: =C14*E14 | G14: =D14*E14 | I14: Budget: Total Cost ≤ Budget | J14: =IF($C$23<=$C$5,"OK","Review")
B15: D | C15: =VLOOKUP(B15,PROJECT_DATA!$A$8:$C$17,2,FALSE) | D15: =VLOOKUP(B15,PROJECT_DATA!$A$8:$C$17,3,FALSE) | E15: 1 | F15: =C15*E15 | G15: =D15*E15 | I15: Binary inputs (0/1) in Select? column | J15: =IF(COUNTIF($E$12:$E$21,"<0")+COUNTIF($E$12:$E$21,">1")=0,"OK","Review")
B16: E | C16: =VLOOKUP(B16,PROJECT_DATA!$A$8:$C$17,2,FALSE) | D16: =VLOOKUP(B16,PROJECT_DATA!$A$8:$C$17,3,FALSE) | E16: 1 | F16: =C16*E16 | G16: =D16*E16 | I16: Exclude low-NPV projects: NPV < cutoff ⇒ Select = 0 | J16: =IF(SUMPRODUCT(--($D$12:$D$21<$F$5),$E$12:$E$21)=0,"OK","Review")
B17: F | C17: =VLOOKUP(B17,PROJECT_DATA!$A$8:$C$17,2,FALSE) | D17: =VLOOKUP(B17,PROJECT_DATA!$A$8:$C$17,3,FALSE) | E17: 1 | F17: =C17*E17 | G17: =D17*E17 | I17: Core group: at least one from A, B, C | J17: =IF($E$12+$E$13+$E$14>=1,"OK","Review")
B18: G | C18: =VLOOKUP(B18,PROJECT_DATA!$A$8:$C$17,2,FALSE) | D18: =VLOOKUP(B18,PROJECT_DATA!$A$8:$C$17,3,FALSE) | E18: 1 | F18: =C18*E18 | G18: =D18*E18 | I18: Include all high-NPV projects (NPV ≥ high cutoff) | J18: =IF(SUMPRODUCT(--($D$12:$D$21>=$F$6),$E$12:$E$21)=SUMPRODUCT(--($D$12:$D$21>=$F$6)),"OK","Review")
B19: H | C19: =VLOOKUP(B19,PROJECT_DATA!$A$8:$C$17,2,FALSE) | D19: =VLOOKUP(B19,PROJECT_DATA!$A$8:$C$17,3,FALSE) | E19: 1 | F19: =C19*E19 | G19: =D19*E19
B20: I | C20: =VLOOKUP(B20,PROJECT_DATA!$A$8:$C$17,2,FALSE) | D20: =VLOOKUP(B20,PROJECT_DATA!$A$8:$C$17,3,FALSE) | E20: 1 | F20: =C20*E20 | G20: =D20*E20 | I20: Overall Status (all checks) | J20: =IF(COUNTIF($J$14:$J$18,"Review")=0,"OK","Review")
B21: J | C21: =VLOOKUP(B21,PROJECT_DATA!$A$8:$C$17,2,FALSE) | D21: =VLOOKUP(B21,PROJECT_DATA!$A$8:$C$17,3,FALSE) | E21: 1 | F21: =C21*E21 | G21: =D21*E21
B22: CALCULATIONS | I22: Solver Setup (enter in Excel Solver)
B23: Total Cost (₹) | C23: =SUM(F12:F21) | I23: Set Objective | J23: C24 (Total NPV)
B24: Total NPV (₹) | C24: =SUM(G12:G21) | I24: To | J24: Max
B25: Budget Slack (₹) | C25: =$C$5-$C$23 | I25: By Changing Variable Cells | J25: E12:E21
B26: Projects Selected (count) | C26: =SUM(E12:E21) | I26: Constraints (core) | J26: C23 <= C5; E12:E21 Binary
I27: Solving Method | J27: Simplex LP
B28: Constraint helper calculations
B29: Cost(ABC) | C29: =SUMPRODUCT(--ISNUMBER(MATCH($B$12:$B$21,{"A","B","C"},0)),$C$12:$C$21,$E$12:$E$21)
B30: Cost(ACF) | C30: =SUMPRODUCT(--ISNUMBER(MATCH($B$12:$B$21,{"A","C","F"},0)),$C$12:$C$21,$E$12:$E$21)
B31: Cost(DEG) | C31: =SUMPRODUCT(--ISNUMBER(MATCH($B$12:$B$21,{"D","E","G"},0)),$C$12:$C$21,$E$12:$E$21)
B32: High-cost count (Cost>₹7,00,000) | C32: =SUMPRODUCT(--($C$12:$C$21>700000),$E$12:$E$21)
B33: NPV/Cost ratio | C33: =IF($C$23=0,"",$C$24/$C$23)

Sheet Caselet_04_FutureVision
A1: Caselet 4 – Investment Planning at FutureVision Ltd.
A2: ⬅ Back to Index
B4: INPUTS | I4: OUTPUTS / DECISION
B5: Capital Budget (₹) | C5: =PROJECT_DATA!$B$5 | I5: Key Outputs
B6: Objective | C6: Maximize Total NPV | I6: Metric | J6: Value
B7: Decision variables | C7: Select? (0/1) for each project | I7: Total Cost (₹) | J7: =C23
B8: Solver note | C8: Objective: C24 (Total NPV). Variable cells: E12:E21 (Binary). Add constraints in Checks. | I8: Total NPV (₹) | J8: =C24
C9: Pre-filled with an optimal solution (computed and saved). You may re-run Solver after changing any input/constraint. | I9: Budget Slack (₹) | J9: =C25
B10: Project Portfolio (Cost & NPV referenced from PROJECT_DATA) | I10: Projects Selected | J10: =C26
B11: Project | C11: Cost (₹) | D11: NPV (₹) | E11: Select? (0/1) | F11: Selected Cost (₹) | G11: Selected NPV (₹)
B12: A | C12: =VLOOKUP(B12,PROJECT_DATA!$A$8:$C$17,2,FALSE) | D12: =VLOOKUP(B12,PROJECT_DATA!$A$8:$C$17,3,FALSE) | E12: 1 | F12: =C12*E12 | G12: =D12*E12 | I12: CHECKS
B13: B | C13: =VLOOKUP(B13,PROJECT_DATA!$A$8:$C$17,2,FALSE) | D13: =VLOOKUP(B13,PROJECT_DATA!$A$8:$C$17,3,FALSE) | E13: 1 | F13: =C13*E13 | G13: =D13*E13 | I13: Check / Constraint | J13: Status
B14: C | C14: =VLOOKUP(B14,PROJECT_DATA!$A$8:$C$17,2,FALSE) | D14: =VLOOKUP(B14,PROJECT_DATA!$A$8:$C$17,3,FALSE) | E14: 1 | F14: =C14*E14 | G14: =D14*E14 | I14: Budget: Total Cost ≤ Budget | J14: =IF($C$23<=$C$5,"OK","Review")
B15: D | C15: =VLOOKUP(B15,PROJECT_DATA!$A$8:$C$17,2,FALSE) | D15: =VLOOKUP(B15,PROJECT_DATA!$A$8:$C$17,3,FALSE) | E15: 1 | F15: =C15*E15 | G15: =D15*E15 | I15: Binary inputs (0/1) in Select? column | J15: =IF(COUNTIF($E$12:$E$21,"<0")+COUNTIF($E$12:$E$21,">1")=0,"OK","Review")
B16: E | C16: =VLOOKUP(B16,PROJECT_DATA!$A$8:$C$17,2,FALSE) | D16: =VLOOKUP(B16,PROJECT_DATA!$A$8:$C$17,3,FALSE) | E16: 1 | F16: =C16*E16 | G16: =D16*E16 | I16: Pairing: A → C (EA ≤ EC) | J16: =IF($E$12<=$E$14,"OK","Review")
B17: F | C17: =VLOOKUP(B17,PROJECT_DATA!$A$8:$C$17,2,FALSE) | D17: =VLOOKUP(B17,PROJECT_DATA!$A$8:$C$17,3,FALSE) | E17: 1 | F17: =C17*E17 | G17: =D17*E17 | I17: Group cap: Cost(A,B,C) ≤ ₹25,00,000 | J17: =IF($C$29<=2500000,"OK","Review")
B18: G | C18: =VLOOKUP(B18,PROJECT_DATA!$A$8:$C$17,2,FALSE) | D18: =VLOOKUP(B18,PROJECT_DATA!$A$8:$C$17,3,FALSE) | E18: 1 | F18: =C18*E18 | G18: =D18*E18
B19: H | C19: =VLOOKUP(B19,PROJECT_DATA!$A$8:$C$17,2,FALSE) | D19: =VLOOKUP(B19,PROJECT_DATA!$A$8:$C$17,3,FALSE) | E19: 1 | F19: =C19*E19 | G19: =D19*E19
B20: I | C20: =VLOOKUP(B20,PROJECT_DATA!$A$8:$C$17,2,FALSE) | D20: =VLOOKUP(B20,PROJECT_DATA!$A$8:$C$17,3,FALSE) | E20: 1 | F20: =C20*E20 | G20: =D20*E20 | I20: Overall Status (all checks) | J20: =IF(COUNTIF($J$14:$J$17,"Review")=0,"OK","Review")
B21: J | C21: =VLOOKUP(B21,PROJECT_DATA!$A$8:$C$17,2,FALSE) | D21: =VLOOKUP(B21,PROJECT_DATA!$A$8:$C$17,3,FALSE) | E21: 1 | F21: =C21*E21 | G21: =D21*E21
B22: CALCULATIONS | I22: Solver Setup (enter in Excel Solver)
B23: Total Cost (₹) | C23: =SUM(F12:F21) | I23: Set Objective | J23: C24 (Total NPV)
B24: Total NPV (₹) | C24: =SUM(G12:G21) | I24: To | J24: Max
B25: Budget Slack (₹) | C25: =$C$5-$C$23 | I25: By Changing Variable Cells | J25: E12:E21
B26: Projects Selected (count) | C26: =SUM(E12:E21) | I26: Constraints (core) | J26: C23 <= C5; E12:E21 Binary
I27: Solving Method | J27: Simplex LP
B28: Constraint helper calculations
B29: Cost(ABC) | C29: =SUMPRODUCT(--ISNUMBER(MATCH($B$12:$B$21,{"A","B","C"},0)),$C$12:$C$21,$E$12:$E$21)
B30: Cost(ACF) | C30: =SUMPRODUCT(--ISNUMBER(MATCH($B$12:$B$21,{"A","C","F"},0)),$C$12:$C$21,$E$12:$E$21)
B31: Cost(DEG) | C31: =SUMPRODUCT(--ISNUMBER(MATCH($B$12:$B$21,{"D","E","G"},0)),$C$12:$C$21,$E$12:$E$21)
B32: High-cost count (Cost>₹7,00,000) | C32: =SUMPRODUCT(--($C$12:$C$21>700000),$E$12:$E$21)
B33: NPV/Cost ratio | C33: =IF($C$23=0,"",$C$24/$C$23)

Sheet Caselet_05_VisionNext
A1: Caselet 5 – Portfolio Optimization at VisionNext Ltd.
A2: ⬅ Back to Index
B4: INPUTS | I4: OUTPUTS / DECISION
B5: Capital Budget (₹) | C5: =PROJECT_DATA!$B$5 | E5: Minimum NPV threshold (₹) | F5: 120000 | I5: Key Outputs
B6: Objective | C6: Maximize Total NPV | I6: Metric | J6: Value
B7: Decision variables | C7: Select? (0/1) for each project | I7: Total Cost (₹) | J7: =C23
B8: Solver note | C8: Objective: C24 (Total NPV). Variable cells: E12:E21 (Binary). Add constraints in Checks. | I8: Total NPV (₹) | J8: =C24
C9: Pre-filled with an optimal solution (computed and saved). You may re-run Solver after changing any input/constraint. | I9: Budget Slack (₹) | J9: =C25
B10: Project Portfolio (Cost & NPV referenced from PROJECT_DATA) | I10: Projects Selected | J10: =C26
B11: Project | C11: Cost (₹) | D11: NPV (₹) | E11: Select? (0/1) | F11: Selected Cost (₹) | G11: Selected NPV (₹)
B12: A | C12: =VLOOKUP(B12,PROJECT_DATA!$A$8:$C$17,2,FALSE) | D12: =VLOOKUP(B12,PROJECT_DATA!$A$8:$C$17,3,FALSE) | E12: 1 | F12: =C12*E12 | G12: =D12*E12 | I12: CHECKS
B13: B | C13: =VLOOKUP(B13,PROJECT_DATA!$A$8:$C$17,2,FALSE) | D13: =VLOOKUP(B13,PROJECT_DATA!$A$8:$C$17,3,FALSE) | E13: 1 | F13: =C13*E13 | G13: =D13*E13 | I13: Check / Constraint | J13: Status
B14: C | C14: =VLOOKUP(B14,PROJECT_DATA!$A$8:$C$17,2,FALSE) | D14: =VLOOKUP(B14,PROJECT_DATA!$A$8:$C$17,3,FALSE) | E14: 1 | F14: =C14*E14 | G14: =D14*E14 | I14: Budget: Total Cost ≤ Budget | J14: =IF($C$23<=$C$5,"OK","Review")
B15: D | C15: =VLOOKUP(B15,PROJECT_DATA!$A$8:$C$17,2,FALSE) | D15: =VLOOKUP(B15,PROJECT_DATA!$A$8:$C$17,3,FALSE) | E15: 1 | F15: =C15*E15 | G15: =D15*E15 | I15: Binary inputs (0/1) in Select? column | J15: =IF(COUNTIF($E$12:$E$21,"<0")+COUNTIF($E$12:$E$21,">1")=0,"OK","Review")
B16: E | C16: =VLOOKUP(B16,PROJECT_DATA!$A$8:$C$17,2,FALSE) | D16: =VLOOKUP(B16,PROJECT_DATA!$A$8:$C$17,3,FALSE) | E16: 1 | F16: =C16*E16 | G16: =D16*E16 | I16: NPV threshold: if NPV < threshold then Select = 0 | J16: =IF(SUMPRODUCT(--($D$12:$D$21<$F$5),$E$12:$E$21)=0,"OK","Review")
B17: F | C17: =VLOOKUP(B17,PROJECT_DATA!$A$8:$C$17,2,FALSE) | D17: =VLOOKUP(B17,PROJECT_DATA!$A$8:$C$17,3,FALSE) | E17: 1 | F17: =C17*E17 | G17: =D17*E17 | I17: Min high-cost projects: count(Cost>₹7,00,000) ≥ 2 | J17: =IF($C$32>=2,"OK","Review")
B18: G | C18: =VLOOKUP(B18,PROJECT_DATA!$A$8:$C$17,2,FALSE) | D18: =VLOOKUP(B18,PROJECT_DATA!$A$8:$C$17,3,FALSE) | E18: 1 | F18: =C18*E18 | G18: =D18*E18 | I18: Conflict: E and F (EE + EF ≤ 1) | J18: =IF($E$16+$E$17<=1,"OK","Review")
B19: H | C19: =VLOOKUP(B19,PROJECT_DATA!$A$8:$C$17,2,FALSE) | D19: =VLOOKUP(B19,PROJECT_DATA!$A$8:$C$17,3,FALSE) | E19: 1 | F19: =C19*E19 | G19: =D19*E19
B20: I | C20: =VLOOKUP(B20,PROJECT_DATA!$A$8:$C$17,2,FALSE) | D20: =VLOOKUP(B20,PROJECT_DATA!$A$8:$C$17,3,FALSE) | E20: 1 | F20: =C20*E20 | G20: =D20*E20 | I20: Overall Status (all checks) | J20: =IF(COUNTIF($J$14:$J$18,"Review")=0,"OK","Review")
B21: J | C21: =VLOOKUP(B21,PROJECT_DATA!$A$8:$C$17,2,FALSE) | D21: =VLOOKUP(B21,PROJECT_DATA!$A$8:$C$17,3,FALSE) | E21: 1 | F21: =C21*E21 | G21: =D21*E21
B22: CALCULATIONS | I22: Solver Setup (enter in Excel Solver)
B23: Total Cost (₹) | C23: =SUM(F12:F21) | I23: Set Objective | J23: C24 (Total NPV)
B24: Total NPV (₹) | C24: =SUM(G12:G21) | I24: To | J24: Max
B25: Budget Slack (₹) | C25: =$C$5-$C$23 | I25: By Changing Variable Cells | J25: E12:E21
B26: Projects Selected (count) | C26: =SUM(E12:E21) | I26: Constraints (core) | J26: C23 <= C5; E12:E21 Binary
I27: Solving Method | J27: Simplex LP
B28: Constraint helper calculations
B29: Cost(ABC) | C29: =SUMPRODUCT(--ISNUMBER(MATCH($B$12:$B$21,{"A","B","C"},0)),$C$12:$C$21,$E$12:$E$21)
B30: Cost(ACF) | C30: =SUMPRODUCT(--ISNUMBER(MATCH($B$12:$B$21,{"A","C","F"},0)),$C$12:$C$21,$E$12:$E$21)
B31: Cost(DEG) | C31: =SUMPRODUCT(--ISNUMBER(MATCH($B$12:$B$21,{"D","E","G"},0)),$C$12:$C$21,$E$12:$E$21)
B32: High-cost count (Cost>₹7,00,000) | C32: =SUMPRODUCT(--($C$12:$C$21>700000),$E$12:$E$21)
B33: NPV/Cost ratio | C33: =IF($C$23=0,"",$C$24/$C$23)

Sheet Caselet_06_GlobalTech
A1: Caselet 6 – Strategic Capital Allocation at GlobalTech Ltd.
A2: ⬅ Back to Index
B4: INPUTS | I4: OUTPUTS / DECISION
B5: Capital Budget (₹) | C5: =PROJECT_DATA!$B$5 | E5: Min NPV/Cost ratio | F5: 0.25 | I5: Key Outputs
B6: Objective | C6: Maximize Total NPV | E6: Max risk spend (% of budget) | F6: 0.3 | I6: Metric | J6: Value
B7: Decision variables | C7: Select? (0/1) for each project | E7: Min strategic spend (% of total cost) | F7: 0.5 | I7: Total Cost (₹) | J7: =C23
B8: Solver note | C8: Objective: C24 (Total NPV). Variable cells: E12:E21 (Binary). Add constraints in Checks. | I8: Total NPV (₹) | J8: =C24
C9: Pre-filled with an optimal solution (computed and saved). You may re-run Solver after changing any input/constraint. | I9: Budget Slack (₹) | J9: =C25
B10: Project Portfolio (Cost & NPV referenced from PROJECT_DATA) | I10: Projects Selected | J10: =C26
B11: Project | C11: Cost (₹) | D11: NPV (₹) | E11: Select? (0/1) | F11: Selected Cost (₹) | G11: Selected NPV (₹)
B12: A | C12: =VLOOKUP(B12,PROJECT_DATA!$A$8:$C$17,2,FALSE) | D12: =VLOOKUP(B12,PROJECT_DATA!$A$8:$C$17,3,FALSE) | E12: 1 | F12: =C12*E12 | G12: =D12*E12 | I12: CHECKS
B13: B | C13: =VLOOKUP(B13,PROJECT_DATA!$A$8:$C$17,2,FALSE) | D13: =VLOOKUP(B13,PROJECT_DATA!$A$8:$C$17,3,FALSE) | E13: 1 | F13: =C13*E13 | G13: =D13*E13 | I13: Check / Constraint | J13: Status
B14: C | C14: =VLOOKUP(B14,PROJECT_DATA!$A$8:$C$17,2,FALSE) | D14: =VLOOKUP(B14,PROJECT_DATA!$A$8:$C$17,3,FALSE) | E14: 1 | F14: =C14*E14 | G14: =D14*E14 | I14: Budget: Total Cost ≤ Budget | J14: =IF($C$23<=$C$5,"OK","Review")
B15: D | C15: =VLOOKUP(B15,PROJECT_DATA!$A$8:$C$17,2,FALSE) | D15: =VLOOKUP(B15,PROJECT_DATA!$A$8:$C$17,3,FALSE) | E15: 1 | F15: =C15*E15 | G15: =D15*E15 | I15: Binary inputs (0/1) in Select? column | J15: =IF(COUNTIF($E$12:$E$21,"<0")+COUNTIF($E$12:$E$21,">1")=0,"OK","Review")
B16: E | C16: =VLOOKUP(B16,PROJECT_DATA!$A$8:$C$17,2,FALSE) | D16: =VLOOKUP(B16,PROJECT_DATA!$A$8:$C$17,3,FALSE) | E16: 1 | F16: =C16*E16 | G16: =D16*E16 | I16: Strategic allocation: Cost(ACF) ≥ 50% of Total Cost | J16: =IF($C$23=0,"Review",IF($C$30>=$F$7*$C$23,"OK","Review"))
B17: F | C17: =VLOOKUP(B17,PROJECT_DATA!$A$8:$C$17,2,FALSE) | D17: =VLOOKUP(B17,PROJECT_DATA!$A$8:$C$17,3,FALSE) | E17: 1 | F17: =C17*E17 | G17: =D17*E17 | I17: Risk cap: Cost(D,E,G) ≤ 30% of Budget | J17: =IF($C$31<=$F$6*$C$5,"OK","Review")
B18: G | C18: =VLOOKUP(B18,PROJECT_DATA!$A$8:$C$17,2,FALSE) | D18: =VLOOKUP(B18,PROJECT_DATA!$A$8:$C$17,3,FALSE) | E18: 1 | F18: =C18*E18 | G18: =D18*E18 | I18: Portfolio efficiency: NPV/Cost ≥ minimum ratio | J18: =IF($C$23=0,"Review",IF($C$33>=$F$5,"OK","Review"))
B19: H | C19: =VLOOKUP(B19,PROJECT_DATA!$A$8:$C$17,2,FALSE) | D19: =VLOOKUP(B19,PROJECT_DATA!$A$8:$C$17,3,FALSE) | E19: 1 | F19: =C19*E19 | G19: =D19*E19
B20: I | C20: =VLOOKUP(B20,PROJECT_DATA!$A$8:$C$17,2,FALSE) | D20: =VLOOKUP(B20,PROJECT_DATA!$A$8:$C$17,3,FALSE) | E20: 1 | F20: =C20*E20 | G20: =D20*E20 | I20: Overall Status (all checks) | J20: =IF(COUNTIF($J$14:$J$18,"Review")=0,"OK","Review")
B21: J | C21: =VLOOKUP(B21,PROJECT_DATA!$A$8:$C$17,2,FALSE) | D21: =VLOOKUP(B21,PROJECT_DATA!$A$8:$C$17,3,FALSE) | E21: 1 | F21: =C21*E21 | G21: =D21*E21
B22: CALCULATIONS | I22: Solver Setup (enter in Excel Solver)
B23: Total Cost (₹) | C23: =SUM(F12:F21) | I23: Set Objective | J23: C24 (Total NPV)
B24: Total NPV (₹) | C24: =SUM(G12:G21) | I24: To | J24: Max
B25: Budget Slack (₹) | C25: =$C$5-$C$23 | I25: By Changing Variable Cells | J25: E12:E21
B26: Projects Selected (count) | C26: =SUM(E12:E21) | I26: Constraints (core) | J26: C23 <= C5; E12:E21 Binary
I27: Solving Method | J27: Simplex LP
B28: Constraint helper calculations
B29: Cost(ABC) | C29: =SUMPRODUCT(--ISNUMBER(MATCH($B$12:$B$21,{"A","B","C"},0)),$C$12:$C$21,$E$12:$E$21)
B30: Cost(ACF) | C30: =SUMPRODUCT(--ISNUMBER(MATCH($B$12:$B$21,{"A","C","F"},0)),$C$12:$C$21,$E$12:$E$21)
B31: Cost(DEG) | C31: =SUMPRODUCT(--ISNUMBER(MATCH($B$12:$B$21,{"D","E","G"},0)),$C$12:$C$21,$E$12:$E$21)
B32: High-cost count (Cost>₹7,00,000) | C32: =SUMPRODUCT(--($C$12:$C$21>700000),$E$12:$E$21)
B33: NPV/Cost ratio | C33: =IF($C$23=0,"",$C$24/$C$23)

Sheet CHECKS_SUMMARY
A1: Checks Summary (All Caselets)
A3: This sheet pulls key outputs and overall status from each caselet sheet.
A5: Caselet | B5: Company | C5: Total Cost (₹) | D5: Total NPV (₹) | E5: Overall Status | F5: Open
A6: Caselet 1 | B6: Optimus Solutions | C6: =Caselet_01_Optimus!$J$7 | D6: =Caselet_01_Optimus!$J$8 | E6: =Caselet_01_Optimus!$J$20 | F6: Open ➜
A7: Caselet 2 | B7: NovaTech Inc. | C7: =Caselet_02_NovaTech!$J$7 | D7: =Caselet_02_NovaTech!$J$8 | E7: =Caselet_02_NovaTech!$J$20 | F7: Open ➜
A8: Caselet 3 | B8: InnovateCorp | C8: =Caselet_03_InnovateCorp!$J$7 | D8: =Caselet_03_InnovateCorp!$J$8 | E8: =Caselet_03_InnovateCorp!$J$20 | F8: Open ➜
A9: Caselet 4 | B9: FutureVision Ltd. | C9: =Caselet_04_FutureVision!$J$7 | D9: =Caselet_04_FutureVision!$J$8 | E9: =Caselet_04_FutureVision!$J$20 | F9: Open ➜
A10: Caselet 5 | B10: VisionNext Ltd. | C10: =Caselet_05_VisionNext!$J$7 | D10: =Caselet_05_VisionNext!$J$8 | E10: =Caselet_05_VisionNext!$J$20 | F10: Open ➜
A11: Caselet 6 | B11: GlobalTech Ltd. | C11: =Caselet_06_GlobalTech!$J$7 | D11: =Caselet_06_GlobalTech!$J$8 | E11: =Caselet_06_GlobalTech!$J$20 | F11: Open ➜
